arka/__init__.py
arka/__main__.py
arka/_crypto.cp313-win_amd64.pyd
arka/block.py
arka/broker.py
arka/chain.py
arka/cryptomodule.c
arka/ed25519.h
arka/keccak.h
arka/net.py
arka-0.0.4.dist-info/licenses/LICENSE
arka-0.0.4.dist-info/METADATA
arka-0.0.4.dist-info/WHEEL
arka-0.0.4.dist-info/top_level.txt
arka-0.0.4.dist-info/RECORD
