Metadata-Version: 2.4
Name: arka
Version: 0.0.4
Summary: A community managed digital money supply
Author-email: "T. R. Stovall" <arkacoin.io@gmail.com>
Maintainer-email: "T. R. Stovall" <arkacoin.io@gmail.com>
License-Expression: MIT
Project-URL: Repository, https://github.com/trstovall/arka.git
Keywords: arka,block,chain,blockchain,ledger,crypto,currency,money,fintech
Classifier: Programming Language :: Python
Requires-Python: >=3.10, <4
License-File: LICENSE
Dynamic: license-file
Dynamic: requires-python
